Backend/__init__.py
Backend/app.py
assignment_counter-0.2.dist-info/METADATA
assignment_counter-0.2.dist-info/WHEEL
assignment_counter-0.2.dist-info/top_level.txt
assignment_counter-0.2.dist-info/RECORD
