Metadata-Version: 2.1
Name: assignment-counter
Version: 0.2
Requires-Dist: Flask
